pyvid.py
pyvid-0.1.2.dist-info/entry_points.txt
pyvid-0.1.2.dist-info/LICENSE.md
pyvid-0.1.2.dist-info/WHEEL
pyvid-0.1.2.dist-info/METADATA
pyvid-0.1.2.dist-info/RECORD
